esgpull/__init__.py
esgpull/config.py
esgpull/constants.py
esgpull/context.py
esgpull/database.py
esgpull/download.py
esgpull/esgpull.py
esgpull/exceptions.py
esgpull/fs.py
esgpull/graph.py
esgpull/install_config.py
esgpull/plugin.py
esgpull/processor.py
esgpull/py.typed
esgpull/result.py
esgpull/tui.py
esgpull/utils.py
esgpull/version.py
esgpull/cli/__init__.py
esgpull/cli/add.py
esgpull/cli/autoremove.py
esgpull/cli/config.py
esgpull/cli/convert.py
esgpull/cli/decorators.py
esgpull/cli/download.py
esgpull/cli/facet.py
esgpull/cli/get.py
esgpull/cli/index_nodes.py
esgpull/cli/install.py
esgpull/cli/plugins.py
esgpull/cli/remove.py
esgpull/cli/retry.py
esgpull/cli/search.py
esgpull/cli/self.py
esgpull/cli/show.py
esgpull/cli/status.py
esgpull/cli/track.py
esgpull/cli/update.py
esgpull/cli/utils.py
esgpull/migrations/README
esgpull/migrations/env.py
esgpull/migrations/script.py.mako
esgpull/migrations/versions/0.3.0_update_tables.py
esgpull/migrations/versions/0.3.1_update_tables.py
esgpull/migrations/versions/0.3.2_update_tables.py
esgpull/migrations/versions/0.3.3_update_tables.py
esgpull/migrations/versions/0.3.4_update_tables.py
esgpull/migrations/versions/0.3.5_update_tables.py
esgpull/migrations/versions/0.3.6_update_tables.py
esgpull/migrations/versions/0.3.7_update_tables.py
esgpull/migrations/versions/0.3.8_update_tables.py
esgpull/migrations/versions/0.4.0_update_tables.py
esgpull/migrations/versions/0.5.0_update_tables.py
esgpull/migrations/versions/0.5.1_update_tables.py
esgpull/migrations/versions/0.5.2_update_tables.py
esgpull/migrations/versions/0.5.3_update_tables.py
esgpull/migrations/versions/0.5.4_update_tables.py
esgpull/migrations/versions/0.5.5_update_tables.py
esgpull/migrations/versions/0.6.0_update_tables.py
esgpull/migrations/versions/0.6.1_update_tables.py
esgpull/migrations/versions/0.6.2_update_tables.py
esgpull/migrations/versions/0.6.3_update_tables.py
esgpull/migrations/versions/0.6.4_update_tables.py
esgpull-0.9.4.dist-info/METADATA
esgpull-0.9.4.dist-info/WHEEL
esgpull-0.9.4.dist-info/entry_points.txt
esgpull-0.9.4.dist-info/licenses/LICENSE
esgpull-0.9.4.dist-info/RECORD
