Metadata-Version: 2.4
Name: esgpull
Version: 0.9.4
Summary: ESGF data discovery, download, replication tool
Project-URL: Repository, https://github.com/ESGF/esgf-download
Project-URL: Documentation, https://esgf.github.io/esgf-download/
Author-email: Sven Rodriguez <srodriguez@ipsl.fr>
License: BSD-3-Clause
License-File: LICENSE
Classifier: License :: OSI Approved :: BSD License
Classifier: Programming Language :: Python :: 3
Classifier: Programming Language :: Python :: 3.10
Classifier: Programming Language :: Python :: 3.11
Classifier: Programming Language :: Python :: 3.12
Requires-Python: >=3.10
Requires-Dist: aiofiles>=22.1.0
Requires-Dist: aiostream>=0.4.5
Requires-Dist: alembic>=1.8.1
Requires-Dist: attrs>=22.1.0
Requires-Dist: cattrs>=22.2.0
Requires-Dist: click-params>=0.4.0
Requires-Dist: click>=8.1.3
Requires-Dist: httpx>=0.23.0
Requires-Dist: nest-asyncio>=1.5.6
Requires-Dist: packaging>=25.0
Requires-Dist: platformdirs>=2.6.2
Requires-Dist: pydantic-settings>=2.10.1
Requires-Dist: pydantic>=2.11.7
Requires-Dist: pyopenssl>=22.1.0
Requires-Dist: pyparsing>=3.0.9
Requires-Dist: pyyaml>=6.0
Requires-Dist: rich>=12.6.0
Requires-Dist: setuptools>=65.4.1
Requires-Dist: sqlalchemy>=2.0.0b2
Requires-Dist: tomlkit>=0.11.5
